aikar/__init__.py
aikar/capital_gains.py
aikar/deduction_validation_and_clubbing.py
aikar/exceptions.py
aikar/income_tax.py
aikar-0.1.6.dist-info/licenses/LICENSE
aikar-0.1.6.dist-info/METADATA
aikar-0.1.6.dist-info/WHEEL
aikar-0.1.6.dist-info/top_level.txt
aikar-0.1.6.dist-info/RECORD
