Metadata-Version: 2.4
Name: aikar
Version: 0.1.6
Summary: Aikar helps in Tax calculations using Python.
Home-page: https://github.com/debjitl45/aikar
Author: Debjit Karmakar
Author-email: Debjit Karmakar <karmadebjit@gmail.com>
License: MIT
Project-URL: Homepage, https://github.com/debjitl45/aikar
Requires-Python: >=3.7
License-File: LICENSE
Dynamic: author
Dynamic: home-page
Dynamic: license-file
Dynamic: requires-python
